LICENSE.txt
README.md
pyproject.toml
setup.py
sslyze/__init__.py
sslyze/__main__.py
sslyze/__version__.py
sslyze/errors.py
sslyze/py.typed
sslyze/server_connectivity.py
sslyze/server_setting.py
sslyze.egg-info/PKG-INFO
sslyze.egg-info/SOURCES.txt
sslyze.egg-info/dependency_links.txt
sslyze.egg-info/entry_points.txt
sslyze.egg-info/requires.txt
sslyze.egg-info/top_level.txt
sslyze/cli/__init__.py
sslyze/cli/command_line_parser.py
sslyze/cli/console_output.py
sslyze/cli/server_string_parser.py
sslyze/connection_helpers/__init__.py
sslyze/connection_helpers/http_request_generator.py
sslyze/connection_helpers/http_response_parser.py
sslyze/connection_helpers/opportunistic_tls_helpers.py
sslyze/connection_helpers/tls_connection.py
sslyze/json/__init__.py
sslyze/json/json_output.py
sslyze/json/pydantic_utils.py
sslyze/json/scan_attempt_json.py
sslyze/mozilla_tls_profile/5.7.json
sslyze/mozilla_tls_profile/__init__.py
sslyze/mozilla_tls_profile/tls_config_checker.py
sslyze/plugins/__init__.py
sslyze/plugins/compression_plugin.py
sslyze/plugins/early_data_plugin.py
sslyze/plugins/elliptic_curves_plugin.py
sslyze/plugins/ems_extension_plugin.py
sslyze/plugins/fallback_scsv_plugin.py
sslyze/plugins/heartbleed_plugin.py
sslyze/plugins/http_headers_plugin.py
sslyze/plugins/openssl_ccs_injection_plugin.py
sslyze/plugins/plugin_base.py
sslyze/plugins/scan_commands.py
sslyze/plugins/session_renegotiation_plugin.py
sslyze/plugins/certificate_info/__init__.py
sslyze/plugins/certificate_info/_cert_chain_analyzer.py
sslyze/plugins/certificate_info/_certificate_utils.py
sslyze/plugins/certificate_info/_cli_connector.py
sslyze/plugins/certificate_info/_get_cert_chain.py
sslyze/plugins/certificate_info/_symantec.py
sslyze/plugins/certificate_info/implementation.py
sslyze/plugins/certificate_info/json_output.py
sslyze/plugins/certificate_info/trust_stores/__init__.py
sslyze/plugins/certificate_info/trust_stores/trust_store.py
sslyze/plugins/certificate_info/trust_stores/trust_store_repository.py
sslyze/plugins/certificate_info/trust_stores/pem_files/apple.pem
sslyze/plugins/certificate_info/trust_stores/pem_files/apple.yaml
