Metadata-Version: 2.4
Name: sslyze
Version: 6.2.0
Summary: Fast and powerful SSL/TLS scanning library.
Home-page: https://github.com/nabla-c0d3/sslyze
Author: Alban Diquet
Author-email: nabla.c0d3@gmail.com
License: AGPL
Project-URL: Source, https://github.com/nabla-c0d3/sslyze
Project-URL: Changelog, https://github.com/nabla-c0d3/sslyze/releases
Project-URL: Documentation, https://nabla-c0d3.github.io/sslyze/documentation
Keywords: ssl tls scan security library
Classifier: Development Status :: 4 - Beta
Classifier: Intended Audience :: Developers
Classifier: Intended Audience :: System Administrators
Classifier: Natural Language :: French
Classifier: License :: OSI Approved :: GNU Affero General Public License v3
Classifier: Programming Language :: Python :: 3.9
Classifier: Programming Language :: Python :: 3.10
Classifier: Programming Language :: Python :: 3.11
Classifier: Programming Language :: Python :: 3.12
Classifier: Programming Language :: Python :: 3.13
Classifier: Topic :: System :: Networking
Classifier: Topic :: System :: Monitoring
Classifier: Topic :: System :: Networking :: Monitoring
Classifier: Topic :: Security
Requires-Python: >=3.9
License-File: LICENSE.txt
Requires-Dist: nassl<6,>=5.3.1
Requires-Dist: cryptography<45,>=43
Requires-Dist: tls-parser<3,>=2
Requires-Dist: pydantic<3,>=2.3
Dynamic: author
Dynamic: author-email
Dynamic: classifier
Dynamic: description
Dynamic: description-content-type
Dynamic: home-page
Dynamic: keywords
Dynamic: license
Dynamic: license-file
Dynamic: project-url
Dynamic: requires-dist
Dynamic: requires-python
Dynamic: summary
